boto3utils/__init__.py
boto3utils/s3.py
boto3utils/s3inventory.py
boto3utils/secrets.py
boto3utils/stepfunctions.py
boto3utils/version.py
boto3_utils-0.4.2.dist-info/LICENSE
boto3_utils-0.4.2.dist-info/METADATA
boto3_utils-0.4.2.dist-info/WHEEL
boto3_utils-0.4.2.dist-info/dependency_links.txt
boto3_utils-0.4.2.dist-info/top_level.txt
boto3_utils-0.4.2.dist-info/RECORD
