Metadata-Version: 2.1
Name: boto3-utils
Version: 0.4.2
Summary: Convenience functions for AWS using boto3
Home-page: https://github.com/matthewhanson/boto3-utils
Author: Matthew Hanson
Author-email: matt.a.hanson@gmail.com
License: MIT
Classifier: Intended Audience :: Developers
Classifier: License :: OSI Approved :: MIT License
Classifier: Programming Language :: Python :: 3.9
Classifier: Programming Language :: Python :: 3.10
Classifier: Programming Language :: Python :: 3.11
License-File: LICENSE
Requires-Dist: boto3 >=1.9
